{
  "$schema": "../gen/schemas/desktop-schema.json",
  "identifier": "default",
  "description": "CodeShelf default permissions",
  "windows": [
    "main"
  ],
  "permissions": [
    "core:default",
    "core:window:allow-close",
    "core:window:allow-minimize",
    "core:window:allow-maximize",
    "core:window:allow-unmaximize",
    "core:window:allow-toggle-maximize",
    "core:window:allow-is-maximized",
    "core:window:allow-start-dragging",
    "core:window:allow-show",
    "core:window:allow-hide",
    "core:window:allow-set-focus",
    "core:window:allow-is-visible",
    "core:window:allow-is-focused",
    "core:window:allow-is-minimized",
    "core:window:allow-unminimize",
    "core:tray:default",
    "core:menu:default",
    "shell:allow-open",
    "dialog:allow-open",
    "dialog:allow-save",
    "dialog:allow-message",
    "dialog:allow-ask",
    "dialog:allow-confirm",
    "fs:allow-read",
    "fs:allow-read-dir",
    "fs:allow-write",
    "fs:allow-read-text-file",
    "fs:allow-write-text-file",
    "fs:allow-exists",
    "fs:allow-mkdir",
    "fs:allow-remove",
    "fs:allow-rename",
    "fs:allow-copy-file",
    "updater:default",
    "process:allow-restart",
    "process:allow-exit",
    {
      "identifier": "fs:scope",
      "allow": [
        "$APPDATA/**",
        "$APPLOCALDATA/**",
        "$APPCONFIG/**",
        "$APPCACHE/**",
        "$APPLOG/**",
        "$RESOURCE/**",
        "$TEMP/**",
        "$HOME/**"
      ],
      "deny": [
        "$HOME/.ssh/**",
        "$HOME/.aws/**",
        "$HOME/.gnupg/**",
        "$HOME/.docker/**",
        "$HOME/.kube/**",
        "$HOME/Library/Keychains/**",
        "$HOME/Library/Cookies/**",
        "$HOME/Library/Application Support/Google/Chrome/**",
        "$HOME/Library/Application Support/Firefox/**",
        "$HOME/AppData/Local/Microsoft/Credentials/**",
        "$HOME/AppData/Roaming/Microsoft/Credentials/**"
      ]
    }
  ]
}
